[{"manufacturerNo":"361","manufacturerName":"וולבו שוודיה  ","modelNo":"1","modelName":"              CZ30","modelSeries":"             XC90 D5","engineCapacity":"2400"},{"manufacturerNo":"361","manufacturerName":"וולבו שוודיה  ","modelNo":"2","modelName":"              FW44","modelSeries":"            V60 2.0T","engineCapacity":"1999"},{"manufacturerNo":"361","manufacturerName":"וולבו שוודיה  ","modelNo":"3","modelName":"              FW44","modelSeries":"            V60 2.0T","engineCapacity":"1999"},{"manufacturerNo":"361","manufacturerName":"וולבו שוודיה  ","modelNo":"4","modelName":"              FW44","modelSeries":"            V60 2.0T","engineCapacity":"1999"},{"manufacturerNo":"361","manufacturerName":"וולבו שוודיה  ","modelNo":"5","modelName":"              AS44","modelSeries":"            S80 2.0T","engineCapacity":"1999"},{"manufacturerNo":"361","manufacturerName":"וולבו שוודיה  ","modelNo":"6","modelName":"              AS44","modelSeries":"            S80 2.0T","engineCapacity":"1999"},{"manufacturerNo":"361","manufacturerName":"וולבו שוודיה  ","modelNo":"7","modelName":"              AS44","modelSeries":"            S80 2.0T","engineCapacity":"1999"},{"manufacturerNo":"361","manufacturerName":"וולבו שוודיה  ","modelNo":"8","modelName":"              AS48","modelSeries":"              S80 T4","engineCapacity":"1595"},{"manufacturerNo":"361","manufacturerName":"וולבו שוודיה  ","modelNo":"9","modelName":"              AS47","modelSeries":"              S80 T5","engineCapacity":"1999"},{"manufacturerNo":"361","manufacturerName":"וולבו שוודיה  ","modelNo":"10","modelName":"              AS47","modelSeries":"              S80 T5","engineCapacity":"1999"},{"manufacturerNo":"361","manufacturerName":"וולבו שוודיה  ","modelNo":"11","modelName":"              TS94","modelSeries":"                 S80","engineCapacity":"2922"},{"manufacturerNo":"361","manufacturerName":"וולבו שוודיה  ","modelNo":"12","modelName":"              AS47","modelSeries":"              S80 T5","engineCapacity":"1999"},{"manufacturerNo":"361","manufacturerName":"וולבו שוודיה  ","modelNo":"13","modelName":"              FW47","modelSeries":"              V60 T5","engineCapacity":"1999"},{"manufacturerNo":"361","manufacturerName":"וולבו שוודיה  ","modelNo":"14","modelName":"              FW47","modelSeries":"              V60 T5","engineCapacity":"1999"},{"manufacturerNo":"361","manufacturerName":"וולבו שוודיה  ","modelNo":"15","modelName":"              FW47","modelSeries":"              V60 T5","engineCapacity":"1999"},{"manufacturerNo":"361","manufacturerName":"וולבו שוודיה  ","modelNo":"16","modelName":"              AR90","modelSeries":"              S80 T6","engineCapacity":"2953"},{"manufacturerNo":"361","manufacturerName":"וולבו שוודיה  ","modelNo":"17","modelName":"              AS88","modelSeries":"              S80 D3","engineCapacity":"1984"},{"manufacturerNo":"361","manufacturerName":"וולבו שוודיה  ","modelNo":"18","modelName":"              AS88","modelSeries":"              S80 D3","engineCapacity":"1984"},{"manufacturerNo":"361","manufacturerName":"וולבו שוודיה  ","modelNo":"19","modelName":"              AS48","modelSeries":"              S80 T4","engineCapacity":"1595"},{"manufacturerNo":"361","manufacturerName":"וולבו שוודיה  ","modelNo":"20","modelName":"              BZ82","modelSeries":"             XC70 D5","engineCapacity":"2400"},{"manufacturerNo":"361","manufacturerName":"וולבו שוודיה  ","modelNo":"21","modelName":"              SZ58","modelSeries":"               V70XC","engineCapacity":"2435"},{"manufacturerNo":"361","manufacturerName":"וולבו שוודיה  ","modelNo":"22","modelName":"              BZ82","modelSeries":"             XC70 D5","engineCapacity":"2400"},{"manufacturerNo":"361","manufacturerName":"וולבו שוודיה  ","modelNo":"23","modelName":"              AS40","modelSeries":"              S80 T5","engineCapacity":"1969"},{"manufacturerNo":"361","manufacturerName":"וולבו שוודיה  ","modelNo":"24","modelName":"              AS40","modelSeries":"              S80 T5","engineCapacity":"1969"},{"manufacturerNo":"361","manufacturerName":"וולבו שוודיה  ","modelNo":"25","modelName":"              AS40","modelSeries":"              S80 T5","engineCapacity":"1969"},{"manufacturerNo":"361","manufacturerName":"וולבו שוודיה  ","modelNo":"26","modelName":"              FS40","modelSeries":"              S60 T5","engineCapacity":"1969"},{"manufacturerNo":"361","manufacturerName":"וולבו שוודיה  ","modelNo":"27","modelName":"              FS40","modelSeries":"              S60 T5","engineCapacity":"1969"},{"manufacturerNo":"361","manufacturerName":"וולבו שוודיה  ","modelNo":"28","modelName":"              FS40","modelSeries":"              S60 T5","engineCapacity":"1969"},{"manufacturerNo":"361","manufacturerName":"וולבו שוודיה  ","modelNo":"29","modelName":"              FS40","modelSeries":"              S60 T5","engineCapacity":"1969"},{"manufacturerNo":"361","manufacturerName":"וולבו שוודיה  ","modelNo":"30","modelName":"              FS40","modelSeries":"              S60 T5","engineCapacity":"1969"},{"manufacturerNo":"361","manufacturerName":"וולבו שוודיה  ","modelNo":"31","modelName":"              TS61","modelSeries":"             S80 2.4","engineCapacity":"2435"},{"manufacturerNo":"361","manufacturerName":"וולבו שוודיה  ","modelNo":"32","modelName":"              FS40","modelSeries":"              S60 T5","engineCapacity":"1969"},{"manufacturerNo":"361","manufacturerName":"וולבו שוודיה  ","modelNo":"33","modelName":"              AS40","modelSeries":"              S80 T5","engineCapacity":"1969"},{"manufacturerNo":"361","manufacturerName":"וולבו שוודיה  ","modelNo":"34","modelName":"              AS40","modelSeries":"              S80 T5","engineCapacity":"1969"},{"manufacturerNo":"361","manufacturerName":"וולבו שוודיה  ","modelNo":"35","modelName":"              AS40","modelSeries":"              S80 T5","engineCapacity":"1969"},{"manufacturerNo":"361","manufacturerName":"וולבו שוודיה  ","modelNo":"36","modelName":"              LCA2","modelSeries":"             XC90 T6","engineCapacity":"1969"},{"manufacturerNo":"361","manufacturerName":"וולבו שוודיה  ","modelNo":"37","modelName":"              LFA2","modelSeries":"             XC90 T6","engineCapacity":"1969"},{"manufacturerNo":"361","manufacturerName":"וולבו שוודיה  ","modelNo":"38","modelName":"              LCA2","modelSeries":"             XC90 T6","engineCapacity":"1969"},{"manufacturerNo":"361","manufacturerName":"וולבו שוודיה  ","modelNo":"39","modelName":"              LFA2","modelSeries":"             XC90 T6","engineCapacity":"1969"},{"manufacturerNo":"361","manufacturerName":"וולבו שוודיה  ","modelNo":"40","modelName":"              LFA2","modelSeries":"             XC90 T6","engineCapacity":"1969"},{"manufacturerNo":"361","manufacturerName":"וולבו שוודיה  ","modelNo":"41","modelName":"              TR91","modelSeries":"                 S80","engineCapacity":"2922"},{"manufacturerNo":"361","manufacturerName":"וולבו שוודיה  ","modelNo":"42","modelName":"              LCA4","modelSeries":"             XC90 D5","engineCapacity":"1969"},{"manufacturerNo":"361","manufacturerName":"וולבו שוודיה  ","modelNo":"43","modelName":"              LFA4","modelSeries":"             XC90 D5","engineCapacity":"1969"},{"manufacturerNo":"361","manufacturerName":"וולבו שוודיה  ","modelNo":"44","modelName":"              LCA4","modelSeries":"             XC90 D5","engineCapacity":"1969"},{"manufacturerNo":"361","manufacturerName":"וולבו שוודיה  ","modelNo":"45","modelName":"              LFA4","modelSeries":"             XC90 D5","engineCapacity":"1969"},{"manufacturerNo":"361","manufacturerName":"וולבו שוודיה  ","modelNo":"46","modelName":"              LFA4","modelSeries":"             XC90 D5","engineCapacity":"1969"},{"manufacturerNo":"361","manufacturerName":"וולבו שוודיה  ","modelNo":"47","modelName":"              LCA2","modelSeries":"             XC90 T6","engineCapacity":"1969"},{"manufacturerNo":"361","manufacturerName":"וולבו שוודיה  ","modelNo":"48","modelName":"              LFA2","modelSeries":"             XC90 T6","engineCapacity":"1969"},{"manufacturerNo":"361","manufacturerName":"וולבו שוודיה  ","modelNo":"49","modelName":"              LCA2","modelSeries":"             XC90 T6","engineCapacity":"1969"},{"manufacturerNo":"361","manufacturerName":"וולבו שוודיה  ","modelNo":"50","modelName":"              LFA2","modelSeries":"             XC90 T6","engineCapacity":"1969"},{"manufacturerNo":"361","manufacturerName":"וולבו שוודיה  ","modelNo":"51","modelName":"              TR91","modelSeries":"                 S80","engineCapacity":"2922"},{"manufacturerNo":"361","manufacturerName":"וולבו שוודיה  ","modelNo":"52","modelName":"              LFA2","modelSeries":"             XC90 T6","engineCapacity":"1969"},{"manufacturerNo":"361","manufacturerName":"וולבו שוודיה  ","modelNo":"53","modelName":"              LCA4","modelSeries":"             XC90 D5","engineCapacity":"1969"},{"manufacturerNo":"361","manufacturerName":"וולבו שוודיה  ","modelNo":"54","modelName":"              LFA4","modelSeries":"             XC90 D5","engineCapacity":"1969"},{"manufacturerNo":"361","manufacturerName":"וולבו שוודיה  ","modelNo":"55","modelName":"              LCA4","modelSeries":"             XC90 D5","engineCapacity":"1969"},{"manufacturerNo":"361","manufacturerName":"וולבו שוודיה  ","modelNo":"56","modelName":"              LFA4","modelSeries":"             XC90 D5","engineCapacity":"1969"},{"manufacturerNo":"361","manufacturerName":"וולבו שוודיה  ","modelNo":"57","modelName":"              LFA4","modelSeries":"             XC90 D5","engineCapacity":"1969"},{"manufacturerNo":"361","manufacturerName":"וולבו שוודיה  ","modelNo":"58","modelName":"              LFBA","modelSeries":"             XC90 T8","engineCapacity":"1969"},{"manufacturerNo":"361","manufacturerName":"וולבו שוודיה  ","modelNo":"59","modelName":"              LC68","modelSeries":"             XC90 D5","engineCapacity":"1969"},{"manufacturerNo":"361","manufacturerName":"וולבו שוודיה  ","modelNo":"60","modelName":"              LC68","modelSeries":"             XC90 D5","engineCapacity":"1969"},{"manufacturerNo":"361","manufacturerName":"וולבו שוודיה  ","modelNo":"61","modelName":"              TR92","modelSeries":"                 S80","engineCapacity":"2922"},{"manufacturerNo":"361","manufacturerName":"וולבו שוודיה  ","modelNo":"62","modelName":"              LCA2","modelSeries":"             XC90 T6","engineCapacity":"1969"},{"manufacturerNo":"361","manufacturerName":"וולבו שוודיה  ","modelNo":"63","modelName":"              LFBA","modelSeries":"             XC90 T8","engineCapacity":"1969"},{"manufacturerNo":"361","manufacturerName":"וולבו שוודיה  ","modelNo":"64","modelName":"              LTBA","modelSeries":"             XC90 T8","engineCapacity":"1969"},{"manufacturerNo":"361","manufacturerName":"וולבו שוודיה  ","modelNo":"65","modelName":"              LF68","modelSeries":"             XC90 D5","engineCapacity":"1969"},{"manufacturerNo":"361","manufacturerName":"וולבו שוודיה  ","modelNo":"66","modelName":"              PS10","modelSeries":"              S90 T5","engineCapacity":"1969"},{"manufacturerNo":"361","manufacturerName":"וולבו שוודיה  ","modelNo":"67","modelName":"              PSA2","modelSeries":"              S90 T6","engineCapacity":"1969"},{"manufacturerNo":"361","manufacturerName":"וולבו שוודיה  ","modelNo":"68","modelName":"              PSA2","modelSeries":"              S90 T6","engineCapacity":"1969"},{"manufacturerNo":"361","manufacturerName":"וולבו שוודיה  ","modelNo":"69","modelName":"              FSA0","modelSeries":"              S60 T6","engineCapacity":"1969"},{"manufacturerNo":"361","manufacturerName":"וולבו שוודיה  ","modelNo":"70","modelName":"              PSA2","modelSeries":"              S90 T6","engineCapacity":"1969"},{"manufacturerNo":"361","manufacturerName":"וולבו שוודיה  ","modelNo":"71","modelName":"              TR92","modelSeries":"                 S80","engineCapacity":"2922"},{"manufacturerNo":"361","manufacturerName":"וולבו שוודיה  ","modelNo":"72","modelName":"              PSA2","modelSeries":"              S90 T6","engineCapacity":"1969"},{"manufacturerNo":"361","manufacturerName":"וולבו שוודיה  ","modelNo":"73","modelName":"              LFA2","modelSeries":"             XC90 T6","engineCapacity":"1969"},{"manufacturerNo":"361","manufacturerName":"וולבו שוודיה  ","modelNo":"74","modelName":"              LC68","modelSeries":"             XC90 D5","engineCapacity":"1969"},{"manufacturerNo":"361","manufacturerName":"וולבו שוודיה  ","modelNo":"75","modelName":"              LC68","modelSeries":"             XC90 D5","engineCapacity":"1969"},{"manufacturerNo":"361","manufacturerName":"וולבו שוודיה  ","modelNo":"76","modelName":"              PS10","modelSeries":"              S90 T5","engineCapacity":"1969"},{"manufacturerNo":"361","manufacturerName":"וולבו שוודיה  ","modelNo":"77","modelName":"              FW40","modelSeries":"              V60 T5","engineCapacity":"1969"},{"manufacturerNo":"361","manufacturerName":"וולבו שוודיה  ","modelNo":"78","modelName":"              PZA2","modelSeries":"            V90CC T6","engineCapacity":"1969"},{"manufacturerNo":"361","manufacturerName":"וולבו שוודיה  ","modelNo":"79","modelName":"              LFA2","modelSeries":"             XC90 T6","engineCapacity":"1969"},{"manufacturerNo":"361","manufacturerName":"וולבו שוודיה  ","modelNo":"80","modelName":"              LF68","modelSeries":"             XC90 D5","engineCapacity":"1969"},{"manufacturerNo":"361","manufacturerName":"וולבו שוודיה  ","modelNo":"81","modelName":"              TS61","modelSeries":"                 S80","engineCapacity":"2435"},{"manufacturerNo":"361","manufacturerName":"וולבו שוודיה  ","modelNo":"82","modelName":"              PZA2","modelSeries":"            V90CC T6","engineCapacity":"1969"},{"manufacturerNo":"361","manufacturerName":"וולבו שוודיה  ","modelNo":"83","modelName":"              UZBA","modelSeries":"             XC60 T8","engineCapacity":"1969"},{"manufacturerNo":"361","manufacturerName":"וולבו שוודיה  ","modelNo":"84","modelName":"              UZBA","modelSeries":"             XC60 T8","engineCapacity":"1969"},{"manufacturerNo":"361","manufacturerName":"וולבו שוודיה  ","modelNo":"85","modelName":"              UZBA","modelSeries":"             XC60 T8","engineCapacity":"1969"},{"manufacturerNo":"361","manufacturerName":"וולבו שוודיה  ","modelNo":"86","modelName":"              UZBA","modelSeries":"             XC60 T8","engineCapacity":"1969"},{"manufacturerNo":"361","manufacturerName":"וולבו שוודיה  ","modelNo":"87","modelName":"              UZ10","modelSeries":"             XC60 T5","engineCapacity":"1969"},{"manufacturerNo":"361","manufacturerName":"וולבו שוודיה  ","modelNo":"88","modelName":"              UZ10","modelSeries":"             XC60 T5","engineCapacity":"1969"},{"manufacturerNo":"361","manufacturerName":"וולבו שוודיה  ","modelNo":"89","modelName":"              UZ10","modelSeries":"             XC60 T5","engineCapacity":"1969"},{"manufacturerNo":"361","manufacturerName":"וולבו שוודיה  ","modelNo":"90","modelName":"              UZ68","modelSeries":"             XC60 D5","engineCapacity":"1969"},{"manufacturerNo":"361","manufacturerName":"וולבו שוודיה  ","modelNo":"91","modelName":"              TS61","modelSeries":"                 S80","engineCapacity":"2435"},{"manufacturerNo":"361","manufacturerName":"וולבו שוודיה  ","modelNo":"92","modelName":"              UZ68","modelSeries":"             XC60 D5","engineCapacity":"1969"},{"manufacturerNo":"361","manufacturerName":"וולבו שוודיה  ","modelNo":"93","modelName":"              LFA2","modelSeries":"             XC90 T6","engineCapacity":"1969"},{"manufacturerNo":"361","manufacturerName":"וולבו שוודיה  ","modelNo":"94","modelName":"              LFBA","modelSeries":"             XC90 T8","engineCapacity":"1969"},{"manufacturerNo":"361","manufacturerName":"וולבו שוודיה  ","modelNo":"95","modelName":"              LFA3","modelSeries":"             XC90 T6","engineCapacity":"1969"},{"manufacturerNo":"361","manufacturerName":"וולבו שוודיה  ","modelNo":"96","modelName":"              UZ25","modelSeries":"             XC60 T5","engineCapacity":"1969"},{"manufacturerNo":"361","manufacturerName":"וולבו שוודיה  ","modelNo":"97","modelName":"              UZ25","modelSeries":"             XC60 T5","engineCapacity":"1969"},{"manufacturerNo":"361","manufacturerName":"וולבו שוודיה  ","modelNo":"98","modelName":"              UZ68","modelSeries":"             XC60 D5","engineCapacity":"1969"},{"manufacturerNo":"361","manufacturerName":"וולבו שוודיה  ","modelNo":"99","modelName":"              UZ68","modelSeries":"             XC60 D5","engineCapacity":"1969"},{"manufacturerNo":"361","manufacturerName":"וולבו שוודיה  ","modelNo":"100","modelName":"              XZ13","modelSeries":"             XC40 T5","engineCapacity":"1969"},{"manufacturerNo":"361","manufacturerName":"וולבו שוודיה  ","modelNo":"101","modelName":"              TS79","modelSeries":"                 S80","engineCapacity":"2401"},{"manufacturerNo":"361","manufacturerName":"וולבו שוודיה  ","modelNo":"102","modelName":"              XZ13","modelSeries":"             XC40 T5","engineCapacity":"1969"},{"manufacturerNo":"361","manufacturerName":"וולבו שוודיה  ","modelNo":"103","modelName":"              XZ13","modelSeries":"             XC40 T5","engineCapacity":"1969"},{"manufacturerNo":"361","manufacturerName":"וולבו שוודיה  ","modelNo":"104","modelName":"              UZ68","modelSeries":"             XC60 D5","engineCapacity":"1969"},{"manufacturerNo":"361","manufacturerName":"וולבו שוודיה  ","modelNo":"105","modelName":"              UZ25","modelSeries":"             XC60 T5","engineCapacity":"1969"},{"manufacturerNo":"361","manufacturerName":"וולבו שוודיה  ","modelNo":"106","modelName":"              UZBM","modelSeries":"             XC60 T8","engineCapacity":"1969"},{"manufacturerNo":"361","manufacturerName":"וולבו שוודיה  ","modelNo":"107","modelName":"              UZBM","modelSeries":"             XC60 T8","engineCapacity":"1969"},{"manufacturerNo":"361","manufacturerName":"וולבו שוודיה  ","modelNo":"108","modelName":"              UZ25","modelSeries":"             XC60 T5","engineCapacity":"1969"},{"manufacturerNo":"361","manufacturerName":"וולבו שוודיה  ","modelNo":"109","modelName":"              UZ68","modelSeries":"             XC60 D5","engineCapacity":"1969"},{"manufacturerNo":"361","manufacturerName":"וולבו שוודיה  ","modelNo":"110","modelName":"              UZBM","modelSeries":"             XC60 T8","engineCapacity":"1969"},{"manufacturerNo":"361","manufacturerName":"וולבו שוודיה  ","modelNo":"111","modelName":"              TS79","modelSeries":"                 S80","engineCapacity":"2401"},{"manufacturerNo":"361","manufacturerName":"וולבו שוודיה  ","modelNo":"112","modelName":"              LF68","modelSeries":"             XC90 D5","engineCapacity":"1969"},{"manufacturerNo":"361","manufacturerName":"וולבו שוודיה  ","modelNo":"113","modelName":"              LFBM","modelSeries":"             XC90 T8","engineCapacity":"1969"},{"manufacturerNo":"361","manufacturerName":"וולבו שוודיה  ","modelNo":"114","modelName":"              UZBM","modelSeries":"             XC60 T8","engineCapacity":"1969"},{"manufacturerNo":"361","manufacturerName":"וולבו שוודיה  ","modelNo":"115","modelName":"              UZ25","modelSeries":"             XC60 T5","engineCapacity":"1969"},{"manufacturerNo":"361","manufacturerName":"וולבו שוודיה  ","modelNo":"121","modelName":"              TS49","modelSeries":"                 S80","engineCapacity":"1984"},{"manufacturerNo":"361","manufacturerName":"וולבו שוודיה  ","modelNo":"131","modelName":"              TS49","modelSeries":"                 S80","engineCapacity":"1984"},{"manufacturerNo":"361","manufacturerName":"וולבו שוודיה  ","modelNo":"141","modelName":"            940 GL","modelSeries":"                    ","engineCapacity":"1986"},{"manufacturerNo":"361","manufacturerName":"וולבו שוודיה  ","modelNo":"151","modelName":"            940 GL","modelSeries":"                    ","engineCapacity":"1986"},{"manufacturerNo":"361","manufacturerName":"וולבו שוודיה  ","modelNo":"161","modelName":"           940 GLE","modelSeries":"                    ","engineCapacity":"1986"},{"manufacturerNo":"361","manufacturerName":"וולבו שוודיה  ","modelNo":"171","modelName":"           940 GLE","modelSeries":"                    ","engineCapacity":"2316"},{"manufacturerNo":"361","manufacturerName":"וולבו שוודיה  ","modelNo":"181","modelName":"           940 GLE","modelSeries":"                    ","engineCapacity":"2316"},{"manufacturerNo":"361","manufacturerName":"וולבו שוודיה  ","modelNo":"191","modelName":"              AS56","modelSeries":"            S80 2.5T","engineCapacity":"2521"},{"manufacturerNo":"361","manufacturerName":"וולבו שוודיה  ","modelNo":"192","modelName":"              AS56","modelSeries":"            S80 2.5T","engineCapacity":"2521"},{"manufacturerNo":"361","manufacturerName":"וולבו שוודיה  ","modelNo":"201","modelName":"              AS56","modelSeries":"            S80 2.5T","engineCapacity":"2521"},{"manufacturerNo":"361","manufacturerName":"וולבו שוודיה  ","modelNo":"202","modelName":"              AS56","modelSeries":"            S80 2.5T","engineCapacity":"2521"},{"manufacturerNo":"361","manufacturerName":"וולבו שוודיה  ","modelNo":"211","modelName":"              AS98","modelSeries":"             S80 3.2","engineCapacity":"3192"},{"manufacturerNo":"361","manufacturerName":"וולבו שוודיה  ","modelNo":"212","modelName":"              AS98","modelSeries":"             S80 3.2","engineCapacity":"3192"},{"manufacturerNo":"361","manufacturerName":"וולבו שוודיה  ","modelNo":"221","modelName":"            944-21","modelSeries":"             940-GLE","engineCapacity":"1986"},{"manufacturerNo":"361","manufacturerName":"וולבו שוודיה  ","modelNo":"231","modelName":"              AS98","modelSeries":"             S80 3.2","engineCapacity":"3192"},{"manufacturerNo":"361","manufacturerName":"וולבו שוודיה  ","modelNo":"232","modelName":"              AS98","modelSeries":"             S80 3.2","engineCapacity":"3192"},{"manufacturerNo":"361","manufacturerName":"וולבו שוודיה  ","modelNo":"241","modelName":"            964-95","modelSeries":"             S90-3.0","engineCapacity":"2922"},{"manufacturerNo":"361","manufacturerName":"וולבו שוודיה  ","modelNo":"251","modelName":"            964-96","modelSeries":"                S-90","engineCapacity":"2922"},{"manufacturerNo":"361","manufacturerName":"וולבו שוודיה  ","modelNo":"261","modelName":"              TS97","modelSeries":"             S80-2.9","engineCapacity":"2922"},{"manufacturerNo":"361","manufacturerName":"וולבו שוודיה  ","modelNo":"271","modelName":"              AS85","modelSeries":"              S80 V8","engineCapacity":"4414"},{"manufacturerNo":"361","manufacturerName":"וולבו שוודיה  ","modelNo":"272","modelName":"              AS85","modelSeries":"              S80 V8","engineCapacity":"4414"},{"manufacturerNo":"361","manufacturerName":"וולבו שוודיה  ","modelNo":"281","modelName":"              AS85","modelSeries":"              S80 V8","engineCapacity":"4414"},{"manufacturerNo":"361","manufacturerName":"וולבו שוודיה  ","modelNo":"282","modelName":"              AS85","modelSeries":"              S80 V8","engineCapacity":"4414"},{"manufacturerNo":"361","manufacturerName":"וולבו שוודיה  ","modelNo":"291","modelName":"              AS71","modelSeries":"              S80 D5","engineCapacity":"2400"},{"manufacturerNo":"361","manufacturerName":"וולבו שוודיה  ","modelNo":"292","modelName":"              AS71","modelSeries":"              S80 D5","engineCapacity":"2400"},{"manufacturerNo":"361","manufacturerName":"וולבו שוודיה  ","modelNo":"301","modelName":"            944-81","modelSeries":"             940 GLE","engineCapacity":"2316"},{"manufacturerNo":"361","manufacturerName":"וולבו שוודיה  ","modelNo":"311","modelName":"              AS71","modelSeries":"              S80 D5","engineCapacity":"2400"},{"manufacturerNo":"361","manufacturerName":"וולבו שוודיה  ","modelNo":"312","modelName":"              AS71","modelSeries":"              S80 D5","engineCapacity":"2400"},{"manufacturerNo":"361","manufacturerName":"וולבו שוודיה  ","modelNo":"321","modelName":"            945-81","modelSeries":"             940 GLE","engineCapacity":"2316"},{"manufacturerNo":"361","manufacturerName":"וולבו שוודיה  ","modelNo":"331","modelName":"              MC67","modelSeries":"              C70 T5","engineCapacity":"2521"},{"manufacturerNo":"361","manufacturerName":"וולבו שוודיה  ","modelNo":"341","modelName":"              AS99","modelSeries":"              S80 T6","engineCapacity":"2953"},{"manufacturerNo":"361","manufacturerName":"וולבו שוודיה  ","modelNo":"351","modelName":"              AS99","modelSeries":"              S80 T6","engineCapacity":"2953"},{"manufacturerNo":"361","manufacturerName":"וולבו שוודיה  ","modelNo":"361","modelName":"              CM71","modelSeries":"             XC90 D5","engineCapacity":"2400"},{"manufacturerNo":"361","manufacturerName":"וולבו שוודיה  ","modelNo":"371","modelName":"              CM71","modelSeries":"             XC90 D5","engineCapacity":"2400"},{"manufacturerNo":"361","manufacturerName":"וולבו שוודיה  ","modelNo":"381","modelName":"              CZ71","modelSeries":"             XC90 D5","engineCapacity":"2400"},{"manufacturerNo":"361","manufacturerName":"וולבו שוודיה  ","modelNo":"391","modelName":"              CZ71","modelSeries":"             XC90 D5","engineCapacity":"2400"},{"manufacturerNo":"361","manufacturerName":"וולבו שוודיה  ","modelNo":"401","modelName":"              CM98","modelSeries":"            XC90 3.2","engineCapacity":"3192"},{"manufacturerNo":"361","manufacturerName":"וולבו שוודיה  ","modelNo":"411","modelName":"              CM98","modelSeries":"            XC90 3.2","engineCapacity":"3192"},{"manufacturerNo":"361","manufacturerName":"וולבו שוודיה  ","modelNo":"421","modelName":"              SZ59","modelSeries":"              XC70 T","engineCapacity":"2521"},{"manufacturerNo":"361","manufacturerName":"וולבו שוודיה  ","modelNo":"422","modelName":"              SZ59","modelSeries":"              XC70 T","engineCapacity":"2521"},{"manufacturerNo":"361","manufacturerName":"וולבו שוודיה  ","modelNo":"431","modelName":"              CZ98","modelSeries":"            XC90 3.2","engineCapacity":"3192"},{"manufacturerNo":"361","manufacturerName":"וולבו שוודיה  ","modelNo":"441","modelName":"              CZ98","modelSeries":"            XC90 3.2","engineCapacity":"3192"},{"manufacturerNo":"361","manufacturerName":"וולבו שוודיה  ","modelNo":"451","modelName":"              CM85","modelSeries":"             XC90 V8","engineCapacity":"4414"},{"manufacturerNo":"361","manufacturerName":"וולבו שוודיה  ","modelNo":"461","modelName":"              CM85","modelSeries":"             XC90 V8","engineCapacity":"4414"},{"manufacturerNo":"361","manufacturerName":"וולבו שוודיה  ","modelNo":"471","modelName":"              CZ85","modelSeries":"             XC90 V8","engineCapacity":"4414"},{"manufacturerNo":"361","manufacturerName":"וולבו שוודיה  ","modelNo":"481","modelName":"              CZ85","modelSeries":"             XC90 V8","engineCapacity":"4414"},{"manufacturerNo":"361","manufacturerName":"וולבו שוודיה  ","modelNo":"491","modelName":"              AR85","modelSeries":"              S80 V8","engineCapacity":"4414"},{"manufacturerNo":"361","manufacturerName":"וולבו שוודיה  ","modelNo":"501","modelName":"            964-95","modelSeries":"             960-3.0","engineCapacity":"2922"},{"manufacturerNo":"361","manufacturerName":"וולבו שוודיה  ","modelNo":"511","modelName":"              BZ98","modelSeries":"        XC70 3.2 AWD","engineCapacity":"3192"},{"manufacturerNo":"361","manufacturerName":"וולבו שוודיה  ","modelNo":"521","modelName":"              BZ98","modelSeries":"        XC70 3.2 AWD","engineCapacity":"3192"},{"manufacturerNo":"361","manufacturerName":"וולבו שוודיה  ","modelNo":"531","modelName":"              BW98","modelSeries":"             V70 3.2","engineCapacity":"3192"},{"manufacturerNo":"361","manufacturerName":"וולבו שוודיה  ","modelNo":"541","modelName":"              BW98","modelSeries":"             V70 3.2","engineCapacity":"3192"},{"manufacturerNo":"361","manufacturerName":"וולבו שוודיה  ","modelNo":"551","modelName":"              BW99","modelSeries":"              V70 T6","engineCapacity":"2953"},{"manufacturerNo":"361","manufacturerName":"וולבו שוודיה  ","modelNo":"561","modelName":"              BW99","modelSeries":"              V70 T6","engineCapacity":"2953"},{"manufacturerNo":"361","manufacturerName":"וולבו שוודיה  ","modelNo":"571","modelName":"              AS60","modelSeries":"            S80 2.5T","engineCapacity":"2521"},{"manufacturerNo":"361","manufacturerName":"וולבו שוודיה  ","modelNo":"581","modelName":"              AS60","modelSeries":"            S80 2.5T","engineCapacity":"2521"},{"manufacturerNo":"361","manufacturerName":"וולבו שוודיה  ","modelNo":"591","modelName":"              CT98","modelSeries":"            XC90 3.2","engineCapacity":"3192"},{"manufacturerNo":"361","manufacturerName":"וולבו שוודיה  ","modelNo":"601","modelName":"              CT98","modelSeries":"            XC90 3.2","engineCapacity":"3192"},{"manufacturerNo":"361","manufacturerName":"וולבו שוודיה  ","modelNo":"611","modelName":"  945GL TURBO 2000","modelSeries":"    945GL TURBO 2000","engineCapacity":"2316"},{"manufacturerNo":"361","manufacturerName":"וולבו שוודיה  ","modelNo":"621","modelName":"              MC68","modelSeries":"              C70 T5","engineCapacity":"2521"},{"manufacturerNo":"361","manufacturerName":"וולבו שוודיה  ","modelNo":"631","modelName":"              MC38","modelSeries":"            C70 2.4I","engineCapacity":"2435"},{"manufacturerNo":"361","manufacturerName":"וולבו שוודיה  ","modelNo":"641","modelName":"              CM59","modelSeries":"              XC 90T","engineCapacity":"2521"},{"manufacturerNo":"361","manufacturerName":"וולבו שוודיה  ","modelNo":"651","modelName":"              CZ59","modelSeries":"                XC90","engineCapacity":"2521"},{"manufacturerNo":"361","manufacturerName":"וולבו שוודיה  ","modelNo":"681","modelName":"              AS56","modelSeries":"                 S80","engineCapacity":"2521"},{"manufacturerNo":"361","manufacturerName":"וולבו שוודיה  ","modelNo":"691","modelName":"              AS56","modelSeries":"                 S80","engineCapacity":"2521"},{"manufacturerNo":"361","manufacturerName":"וולבו שוודיה  ","modelNo":"701","modelName":"              AS71","modelSeries":"                 S80","engineCapacity":"2400"},{"manufacturerNo":"361","manufacturerName":"וולבו שוודיה  ","modelNo":"711","modelName":"              CT85","modelSeries":"             XC90 V8","engineCapacity":"4414"},{"manufacturerNo":"361","manufacturerName":"וולבו שוודיה  ","modelNo":"721","modelName":"              AS60","modelSeries":"            S80 2.5T","engineCapacity":"2521"},{"manufacturerNo":"361","manufacturerName":"וולבו שוודיה  ","modelNo":"731","modelName":"              AR99","modelSeries":"              S80 T6","engineCapacity":"2953"},{"manufacturerNo":"361","manufacturerName":"וולבו שוודיה  ","modelNo":"741","modelName":" 944GLE TURBO 2000","modelSeries":"   944GLE TURBO 2000","engineCapacity":"2316"},{"manufacturerNo":"361","manufacturerName":"וולבו שוודיה  ","modelNo":"751","modelName":"              AS90","modelSeries":"              S80 T6","engineCapacity":"2953"},{"manufacturerNo":"361","manufacturerName":"וולבו שוודיה  ","modelNo":"761","modelName":"              AR90","modelSeries":"              S80 T6","engineCapacity":"2953"},{"manufacturerNo":"361","manufacturerName":"וולבו שוודיה  ","modelNo":"771","modelName":"              CT95","modelSeries":"            XC90 3.2","engineCapacity":"3192"},{"manufacturerNo":"361","manufacturerName":"וולבו שוודיה  ","modelNo":"781","modelName":"              CT95","modelSeries":"            XC90 3.2","engineCapacity":"3192"},{"manufacturerNo":"361","manufacturerName":"וולבו שוודיה  ","modelNo":"791","modelName":"              BZ95","modelSeries":"            XC70 3.2","engineCapacity":"3192"},{"manufacturerNo":"361","manufacturerName":"וולבו שוודיה  ","modelNo":"801","modelName":"              BZ95","modelSeries":"            XC70 3.2","engineCapacity":"3192"},{"manufacturerNo":"361","manufacturerName":"וולבו שוודיה  ","modelNo":"901","modelName":"              SZ79","modelSeries":"             XC70 D5","engineCapacity":"2401"},{"manufacturerNo":"361","manufacturerName":"וולבו שוודיה  ","modelNo":"911","modelName":"              TS79","modelSeries":"                 S80","engineCapacity":"2401"},{"manufacturerNo":"361","manufacturerName":"וולבו שוודיה  ","modelNo":"921","modelName":"              SZ79","modelSeries":"             XC70 D5","engineCapacity":"2401"},{"manufacturerNo":"361","manufacturerName":"וולבו שוודיה  ","modelNo":"931","modelName":"              TS79","modelSeries":"                 S80","engineCapacity":"2401"},{"manufacturerNo":"361","manufacturerName":"וולבו שוודיה  ","modelNo":"941","modelName":"              TS92","modelSeries":"                 S80","engineCapacity":"2922"},{"manufacturerNo":"361","manufacturerName":"וולבו שוודיה  ","modelNo":"951","modelName":"              TS91","modelSeries":"                 S80","engineCapacity":"2922"},{"manufacturerNo":"361","manufacturerName":"וולבו שוודיה  ","modelNo":"961","modelName":"              SZ59","modelSeries":"                XC70","engineCapacity":"2521"},{"manufacturerNo":"361","manufacturerName":"וולבו שוודיה  ","modelNo":"962","modelName":"              SZ59","modelSeries":"                XC70","engineCapacity":"2521"},{"manufacturerNo":"361","manufacturerName":"וולבו שוודיה  ","modelNo":"971","modelName":"              TS90","modelSeries":"                 S80","engineCapacity":"2783"},{"manufacturerNo":"361","manufacturerName":"וולבו שוודיה  ","modelNo":"981","modelName":"              SW53","modelSeries":"                 V70","engineCapacity":"2319"},{"manufacturerNo":"361","manufacturerName":"וולבו שוודיה  ","modelNo":"991","modelName":"              NK53","modelSeries":"                 C70","engineCapacity":"2319"},{"manufacturerNo":"361","manufacturerName":"וולבו שוודיה  ","modelNo":"1001","modelName":"              TS79","modelSeries":"                 S80","engineCapacity":"2401"},{"manufacturerNo":"361","manufacturerName":"וולבו שוודיה  ","modelNo":"1011","modelName":"              PE92","modelSeries":"                 S80","engineCapacity":"2922"},{"manufacturerNo":"361","manufacturerName":"וולבו שוודיה  ","modelNo":"1111","modelName":"              TS92","modelSeries":"                 S80","engineCapacity":"2922"},{"manufacturerNo":"361","manufacturerName":"וולבו שוודיה  ","modelNo":"1121","modelName":"              TS91","modelSeries":"                 S80","engineCapacity":"2922"},{"manufacturerNo":"361","manufacturerName":"וולבו שוודיה  ","modelNo":"1131","modelName":"              SZ59","modelSeries":"                XC70","engineCapacity":"2521"},{"manufacturerNo":"361","manufacturerName":"וולבו שוודיה  ","modelNo":"1132","modelName":"              SZ59","modelSeries":"                XC70","engineCapacity":"2521"},{"manufacturerNo":"361","manufacturerName":"וולבו שוודיה  ","modelNo":"1141","modelName":"            940 GL","modelSeries":"                    ","engineCapacity":"2316"},{"manufacturerNo":"361","manufacturerName":"וולבו שוודיה  ","modelNo":"1151","modelName":" 944GLE TURBO 2000","modelSeries":"   944GLE TURBO 2000","engineCapacity":"2316"},{"manufacturerNo":"361","manufacturerName":"וולבו שוודיה  ","modelNo":"1161","modelName":"           940 GLE","modelSeries":"                    ","engineCapacity":"2316"},{"manufacturerNo":"361","manufacturerName":"וולבו שוודיה  ","modelNo":"1171","modelName":"            940 GL","modelSeries":"                    ","engineCapacity":"2316"},{"manufacturerNo":"361","manufacturerName":"וולבו שוודיה  ","modelNo":"1181","modelName":"   944GLE LPT 2300","modelSeries":"  944GLE  LPT   2300","engineCapacity":"1986"},{"manufacturerNo":"361","manufacturerName":"וולבו שוודיה  ","modelNo":"1421","modelName":"              SZ59","modelSeries":"              XC70 T","engineCapacity":"2521"},{"manufacturerNo":"361","manufacturerName":"וולבו שוודיה  ","modelNo":"1422","modelName":"              SZ59","modelSeries":"              XC70 T","engineCapacity":"2521"},{"manufacturerNo":"361","manufacturerName":"וולבו שוודיה  ","modelNo":"2201","modelName":"  944GL TURBO 2000","modelSeries":"    944GL TURBO 2000","engineCapacity":"1986"},{"manufacturerNo":"361","manufacturerName":"וולבו שוודיה  ","modelNo":"2211","modelName":"  945GL TURBO 2000","modelSeries":"    945GL TURBO 2000","engineCapacity":"1986"},{"manufacturerNo":"361","manufacturerName":"וולבו שוודיה  ","modelNo":"2221","modelName":" 944GLE TURBO 2000","modelSeries":"   944GLE TURBO 2000","engineCapacity":"1986"},{"manufacturerNo":"361","manufacturerName":"וולבו שוודיה  ","modelNo":"2231","modelName":"           S90 2.5","modelSeries":"            S90 2500","engineCapacity":"2473"},{"manufacturerNo":"361","manufacturerName":"וולבו שוודיה  ","modelNo":"2241","modelName":"          S 90_3.0","modelSeries":"            S90 3000","engineCapacity":"2922"},{"manufacturerNo":"361","manufacturerName":"וולבו שוודיה  ","modelNo":"2251","modelName":"         S90 96496","modelSeries":"וולבו שבדיה נוסעים 4","engineCapacity":"2922"},{"manufacturerNo":"361","manufacturerName":"וולבו שוודיה  ","modelNo":"2261","modelName":"      S80 2.9 TS97","modelSeries":"נוסעים 4 דל         ","engineCapacity":"2922"},{"manufacturerNo":"361","manufacturerName":"וולבו שוודיה  ","modelNo":"2271","modelName":"              TS90","modelSeries":"                 S80","engineCapacity":"2783"},{"manufacturerNo":"361","manufacturerName":"וולבו שוודיה  ","modelNo":"2281","modelName":" S90 30 LIMO 96495","modelSeries":"וולוו שבדיה לימוזינה","engineCapacity":"2922"},{"manufacturerNo":"361","manufacturerName":"וולבו שוודיה  ","modelNo":"2291","modelName":"              SW53","modelSeries":"                 V70","engineCapacity":"2319"},{"manufacturerNo":"361","manufacturerName":"וולבו שוודיה  ","modelNo":"2301","modelName":"944GLE  LPT   2300","modelSeries":"  944GLE  LPT   2300","engineCapacity":"2316"},{"manufacturerNo":"361","manufacturerName":"וולבו שוודיה  ","modelNo":"2321","modelName":"945GLE   LPT  2300","modelSeries":"  945GLE   LPT  2300","engineCapacity":"2316"},{"manufacturerNo":"361","manufacturerName":"וולבו שוודיה  ","modelNo":"2331","modelName":"              NK53","modelSeries":"                 C70","engineCapacity":"2319"},{"manufacturerNo":"361","manufacturerName":"וולבו שוודיה  ","modelNo":"2341","modelName":"              TS94","modelSeries":"                 S80","engineCapacity":"2922"},{"manufacturerNo":"361","manufacturerName":"וולבו שוודיה  ","modelNo":"2351","modelName":"              SZ58","modelSeries":"               V70XC","engineCapacity":"2435"},{"manufacturerNo":"361","manufacturerName":"וולבו שוודיה  ","modelNo":"2361","modelName":"              TS61","modelSeries":"             S80 2.4","engineCapacity":"2435"},{"manufacturerNo":"361","manufacturerName":"וולבו שוודיה  ","modelNo":"2371","modelName":"              LFBA","modelSeries":"             XC90 T8","engineCapacity":"1969"},{"manufacturerNo":"361","manufacturerName":"וולבו שוודיה  ","modelNo":"2481","modelName":"     960      2500","modelSeries":"       960      2500","engineCapacity":"2473"},{"manufacturerNo":"361","manufacturerName":"וולבו שוודיה  ","modelNo":"2501","modelName":"     960      3000","modelSeries":"       960      3000","engineCapacity":"2922"}]