[{"manufacturerNo":"734","manufacturerName":"פורד ספרד     ","modelNo":"1","modelName":"               DM2","modelSeries":"                KUGA","engineCapacity":"1596"},{"manufacturerNo":"734","manufacturerName":"פורד ספרד     ","modelNo":"2","modelName":"               DM2","modelSeries":"                KUGA","engineCapacity":"1596"},{"manufacturerNo":"734","manufacturerName":"פורד ספרד     ","modelNo":"3","modelName":"               DM2","modelSeries":"                KUGA","engineCapacity":"1596"},{"manufacturerNo":"734","manufacturerName":"פורד ספרד     ","modelNo":"4","modelName":"               DM2","modelSeries":"                KUGA","engineCapacity":"1596"},{"manufacturerNo":"734","manufacturerName":"פורד ספרד     ","modelNo":"5","modelName":"               DM2","modelSeries":"                KUGA","engineCapacity":"1596"},{"manufacturerNo":"734","manufacturerName":"פורד ספרד     ","modelNo":"6","modelName":"               DM2","modelSeries":"                KUGA","engineCapacity":"1596"},{"manufacturerNo":"734","manufacturerName":"פורד ספרד     ","modelNo":"7","modelName":"               DM2","modelSeries":"                KUGA","engineCapacity":"1498"},{"manufacturerNo":"734","manufacturerName":"פורד ספרד     ","modelNo":"8","modelName":"               DM2","modelSeries":"                KUGA","engineCapacity":"1498"},{"manufacturerNo":"734","manufacturerName":"פורד ספרד     ","modelNo":"9","modelName":"               PJ2","modelSeries":"     TRANSIT CONNECT","engineCapacity":"1499"},{"manufacturerNo":"734","manufacturerName":"פורד ספרד     ","modelNo":"10","modelName":"               DFW","modelSeries":"               FOCUS","engineCapacity":"1596"},{"manufacturerNo":"734","manufacturerName":"פורד ספרד     ","modelNo":"11","modelName":"               DFW","modelSeries":"               FOCUS","engineCapacity":"1596"},{"manufacturerNo":"734","manufacturerName":"פורד ספרד     ","modelNo":"12","modelName":"               DM2","modelSeries":"                KUGA","engineCapacity":"1498"},{"manufacturerNo":"734","manufacturerName":"פורד ספרד     ","modelNo":"13","modelName":"               PJ2","modelSeries":"     TRANSIT CONNECT","engineCapacity":"1499"},{"manufacturerNo":"734","manufacturerName":"פורד ספרד     ","modelNo":"14","modelName":"               DM2","modelSeries":"                KUGA","engineCapacity":"1498"},{"manufacturerNo":"734","manufacturerName":"פורד ספרד     ","modelNo":"15","modelName":"               DM2","modelSeries":"                KUGA","engineCapacity":"1498"},{"manufacturerNo":"734","manufacturerName":"פורד ספרד     ","modelNo":"16","modelName":"               DM2","modelSeries":"                KUGA","engineCapacity":"1498"},{"manufacturerNo":"734","manufacturerName":"פורד ספרד     ","modelNo":"17","modelName":"               DM2","modelSeries":"                KUGA","engineCapacity":"1498"},{"manufacturerNo":"734","manufacturerName":"פורד ספרד     ","modelNo":"18","modelName":"               DM2","modelSeries":"                KUGA","engineCapacity":"1498"},{"manufacturerNo":"734","manufacturerName":"פורד ספרד     ","modelNo":"19","modelName":"               DM2","modelSeries":"                KUGA","engineCapacity":"1498"},{"manufacturerNo":"734","manufacturerName":"פורד ספרד     ","modelNo":"20","modelName":"               DAW","modelSeries":"               FOCUS","engineCapacity":"1596"},{"manufacturerNo":"734","manufacturerName":"פורד ספרד     ","modelNo":"21","modelName":"               DFW","modelSeries":"               FOCUS","engineCapacity":"1988"},{"manufacturerNo":"734","manufacturerName":"פורד ספרד     ","modelNo":"22","modelName":"               DM2","modelSeries":"                KUGA","engineCapacity":"1498"},{"manufacturerNo":"734","manufacturerName":"פורד ספרד     ","modelNo":"23","modelName":"               DM2","modelSeries":"                KUGA","engineCapacity":"1498"},{"manufacturerNo":"734","manufacturerName":"פורד ספרד     ","modelNo":"24","modelName":"               DM2","modelSeries":"                KUGA","engineCapacity":"1498"},{"manufacturerNo":"734","manufacturerName":"פורד ספרד     ","modelNo":"25","modelName":"               DM2","modelSeries":"                KUGA","engineCapacity":"1498"},{"manufacturerNo":"734","manufacturerName":"פורד ספרד     ","modelNo":"26","modelName":"               DM2","modelSeries":"                KUGA","engineCapacity":"1498"},{"manufacturerNo":"734","manufacturerName":"פורד ספרד     ","modelNo":"27","modelName":"               DM2","modelSeries":"                KUGA","engineCapacity":"1498"},{"manufacturerNo":"734","manufacturerName":"פורד ספרד     ","modelNo":"28","modelName":"               DM2","modelSeries":"                KUGA","engineCapacity":"1498"},{"manufacturerNo":"734","manufacturerName":"פורד ספרד     ","modelNo":"29","modelName":"               DM2","modelSeries":"                KUGA","engineCapacity":"1498"},{"manufacturerNo":"734","manufacturerName":"פורד ספרד     ","modelNo":"30","modelName":"               DM2","modelSeries":"                KUGA","engineCapacity":"1498"},{"manufacturerNo":"734","manufacturerName":"פורד ספרד     ","modelNo":"31","modelName":"               DAW","modelSeries":"               FOCUS","engineCapacity":"1988"},{"manufacturerNo":"734","manufacturerName":"פורד ספרד     ","modelNo":"32","modelName":"               DM2","modelSeries":"                KUGA","engineCapacity":"1498"},{"manufacturerNo":"734","manufacturerName":"פורד ספרד     ","modelNo":"33","modelName":"               DM2","modelSeries":"                KUGA","engineCapacity":"1498"},{"manufacturerNo":"734","manufacturerName":"פורד ספרד     ","modelNo":"34","modelName":"               DM2","modelSeries":"                KUGA","engineCapacity":"1498"},{"manufacturerNo":"734","manufacturerName":"פורד ספרד     ","modelNo":"35","modelName":"               DM2","modelSeries":"                KUGA","engineCapacity":"1498"},{"manufacturerNo":"734","manufacturerName":"פורד ספרד     ","modelNo":"36","modelName":"               DM2","modelSeries":"                KUGA","engineCapacity":"1498"},{"manufacturerNo":"734","manufacturerName":"פורד ספרד     ","modelNo":"41","modelName":"               DAW","modelSeries":"               FOCUS","engineCapacity":"1596"},{"manufacturerNo":"734","manufacturerName":"פורד ספרד     ","modelNo":"51","modelName":"               DA3","modelSeries":"               FOCUS","engineCapacity":"1596"},{"manufacturerNo":"734","manufacturerName":"פורד ספרד     ","modelNo":"61","modelName":"               DB3","modelSeries":"               FOCUS","engineCapacity":"1596"},{"manufacturerNo":"734","manufacturerName":"פורד ספרד     ","modelNo":"71","modelName":"               DA3","modelSeries":"               FOCUS","engineCapacity":"1596"},{"manufacturerNo":"734","manufacturerName":"פורד ספרד     ","modelNo":"72","modelName":"               DA3","modelSeries":"               FOCUS","engineCapacity":"1596"},{"manufacturerNo":"734","manufacturerName":"פורד ספרד     ","modelNo":"81","modelName":"               DB3","modelSeries":"               FOCUS","engineCapacity":"1596"},{"manufacturerNo":"734","manufacturerName":"פורד ספרד     ","modelNo":"82","modelName":"               DB3","modelSeries":"               FOCUS","engineCapacity":"1596"},{"manufacturerNo":"734","manufacturerName":"פורד ספרד     ","modelNo":"91","modelName":"               DA3","modelSeries":"               FOCUS","engineCapacity":"1596"},{"manufacturerNo":"734","manufacturerName":"פורד ספרד     ","modelNo":"92","modelName":"               DA3","modelSeries":"               FOCUS","engineCapacity":"1596"},{"manufacturerNo":"734","manufacturerName":"פורד ספרד     ","modelNo":"101","modelName":"               DB3","modelSeries":"               FOCUS","engineCapacity":"1596"},{"manufacturerNo":"734","manufacturerName":"פורד ספרד     ","modelNo":"102","modelName":"               DB3","modelSeries":"               FOCUS","engineCapacity":"1596"},{"manufacturerNo":"734","manufacturerName":"פורד ספרד     ","modelNo":"111","modelName":"               DA3","modelSeries":"               FOCUS","engineCapacity":"1999"},{"manufacturerNo":"734","manufacturerName":"פורד ספרד     ","modelNo":"112","modelName":"               DA3","modelSeries":"               FOCUS","engineCapacity":"1999"},{"manufacturerNo":"734","manufacturerName":"פורד ספרד     ","modelNo":"121","modelName":"               DB3","modelSeries":"               FOCUS","engineCapacity":"1999"},{"manufacturerNo":"734","manufacturerName":"פורד ספרד     ","modelNo":"122","modelName":"               DB3","modelSeries":"               FOCUS","engineCapacity":"1999"},{"manufacturerNo":"734","manufacturerName":"פורד ספרד     ","modelNo":"131","modelName":"               DB3","modelSeries":"               FOCUS","engineCapacity":"1596"},{"manufacturerNo":"734","manufacturerName":"פורד ספרד     ","modelNo":"141","modelName":"               DA3","modelSeries":"               FOCUS","engineCapacity":"1596"},{"manufacturerNo":"734","manufacturerName":"פורד ספרד     ","modelNo":"151","modelName":"               DB3","modelSeries":"               FOCUS","engineCapacity":"1596"},{"manufacturerNo":"734","manufacturerName":"פורד ספרד     ","modelNo":"161","modelName":"               DA3","modelSeries":"               FOCUS","engineCapacity":"1596"},{"manufacturerNo":"734","manufacturerName":"פורד ספרד     ","modelNo":"181","modelName":"               DAW","modelSeries":"               FOCUS","engineCapacity":"1988"},{"manufacturerNo":"734","manufacturerName":"פורד ספרד     ","modelNo":"191","modelName":"               DFW","modelSeries":"               FOCUS","engineCapacity":"1988"},{"manufacturerNo":"734","manufacturerName":"פורד ספרד     ","modelNo":"201","modelName":"               DFW","modelSeries":"               FOCUS","engineCapacity":"1596"},{"manufacturerNo":"734","manufacturerName":"פורד ספרד     ","modelNo":"210","modelName":"               DFW","modelSeries":"               FOCUS","engineCapacity":"1596"},{"manufacturerNo":"734","manufacturerName":"פורד ספרד     ","modelNo":"211","modelName":"               DFW","modelSeries":"               FOCUS","engineCapacity":"1596"},{"manufacturerNo":"734","manufacturerName":"פורד ספרד     ","modelNo":"220","modelName":"               DAW","modelSeries":"               FOCUS","engineCapacity":"1596"},{"manufacturerNo":"734","manufacturerName":"פורד ספרד     ","modelNo":"221","modelName":"               DAW","modelSeries":"               FOCUS","engineCapacity":"1596"},{"manufacturerNo":"734","manufacturerName":"פורד ספרד     ","modelNo":"231","modelName":"               DFW","modelSeries":"               FOCUS","engineCapacity":"1596"},{"manufacturerNo":"734","manufacturerName":"פורד ספרד     ","modelNo":"241","modelName":"               DAW","modelSeries":"               FOCUS","engineCapacity":"1596"},{"manufacturerNo":"734","manufacturerName":"פורד ספרד     ","modelNo":"250","modelName":"               JH1","modelSeries":"              FIESTA","engineCapacity":"1388"},{"manufacturerNo":"734","manufacturerName":"פורד ספרד     ","modelNo":"251","modelName":"               JH1","modelSeries":"              FIESTA","engineCapacity":"1388"},{"manufacturerNo":"734","manufacturerName":"פורד ספרד     ","modelNo":"261","modelName":"               DA3","modelSeries":"               FOCUS","engineCapacity":"1596"},{"manufacturerNo":"734","manufacturerName":"פורד ספרד     ","modelNo":"271","modelName":"               DB3","modelSeries":"               FOCUS","engineCapacity":"1596"},{"manufacturerNo":"734","manufacturerName":"פורד ספרד     ","modelNo":"281","modelName":"               DA3","modelSeries":"               FOCUS","engineCapacity":"1596"},{"manufacturerNo":"734","manufacturerName":"פורד ספרד     ","modelNo":"291","modelName":"               DB3","modelSeries":"               FOCUS","engineCapacity":"1596"},{"manufacturerNo":"734","manufacturerName":"פורד ספרד     ","modelNo":"300","modelName":"               DAW","modelSeries":"               FOCUS","engineCapacity":"1596"},{"manufacturerNo":"734","manufacturerName":"פורד ספרד     ","modelNo":"301","modelName":"         FOCUS-DAW","modelSeries":"               FOCUS","engineCapacity":"1596"},{"manufacturerNo":"734","manufacturerName":"פורד ספרד     ","modelNo":"310","modelName":"         FOCUS-DFW","modelSeries":"               FOCUS","engineCapacity":"1596"},{"manufacturerNo":"734","manufacturerName":"פורד ספרד     ","modelNo":"311","modelName":"               DB3","modelSeries":"               FOCUS","engineCapacity":"1999"},{"manufacturerNo":"734","manufacturerName":"פורד ספרד     ","modelNo":"321","modelName":"               DA3","modelSeries":"               FOCUS","engineCapacity":"1999"},{"manufacturerNo":"734","manufacturerName":"פורד ספרד     ","modelNo":"401","modelName":"         FOCUS-DFW","modelSeries":"               FOCUS","engineCapacity":"1596"},{"manufacturerNo":"734","manufacturerName":"פורד ספרד     ","modelNo":"420","modelName":"  ESCORT TD ES4ZMP","modelSeries":"אסקורט פרטי 4דלת'   ","engineCapacity":"1753"},{"manufacturerNo":"734","manufacturerName":"פורד ספרד     ","modelNo":"430","modelName":"      YOUTH הטסאיפ","modelSeries":"פיאסטה HTUOY 5 דלתות","engineCapacity":"1299"},{"manufacturerNo":"734","manufacturerName":"פורד ספרד     ","modelNo":"431","modelName":"        CLX טרוקסא","modelSeries":"פורד ספרד הרכבה ספרד","engineCapacity":"1597"},{"manufacturerNo":"734","manufacturerName":"פורד ספרד     ","modelNo":"441","modelName":"               DA3","modelSeries":"               FOCUS","engineCapacity":"1596"},{"manufacturerNo":"734","manufacturerName":"פורד ספרד     ","modelNo":"500","modelName":"  ESCORT TD ES4DMP","modelSeries":"נוסעים פרטי 4 דלתות ","engineCapacity":"1753"},{"manufacturerNo":"734","manufacturerName":"פורד ספרד     ","modelNo":"510","modelName":" ESCORT TD ES4DMP ","modelSeries":"נוסעים פרטי 4 דלתות ","engineCapacity":"1753"},{"manufacturerNo":"734","manufacturerName":"פורד ספרד     ","modelNo":"1510","modelName":" ביטקא.ס CLXטרוקסא","modelSeries":"אסקורט סופר אקטיב 5 ","engineCapacity":"1597"},{"manufacturerNo":"734","manufacturerName":"פורד ספרד     ","modelNo":"1520","modelName":" ביטקא.ס CLXטרוקסא","modelSeries":"אסקורט סופר אקטיב 4 ","engineCapacity":"1597"}]